Metadata-Version: 1.1
Name: segancha
Version: 0.0.1
Summary: Segancha colors model
Home-page: https://github.com/gywn/segancha
Author: UNKNOWN
Author-email: UNKNOWN
License: UNKNOWN
Download-URL: https://github.com/gywn/segancha/archive/v0.0.1.tar.gz
Platform: UNKNOWN
